xraylib_numba/__init__.py
xraylib_numba/config.py
xraylib_numba/config.toml
xraylib_numba/xraylib_overloads.py
xraylib_numba-0.1.0.data/data/__init__.py
xraylib_numba-0.1.0.data/data/config.py
xraylib_numba-0.1.0.data/data/config.toml
xraylib_numba-0.1.0.data/data/xraylib_overloads.py
xraylib_numba-0.1.0.dist-info/entry_points.txt
xraylib_numba-0.1.0.dist-info/LICENSE
xraylib_numba-0.1.0.dist-info/WHEEL
xraylib_numba-0.1.0.dist-info/METADATA
xraylib_numba-0.1.0.dist-info/RECORD
